{
  "asin": "B014KNY5SU",
  "productTitle": "Wella ウエラトーン 2+1 白髪染め クリームタイプ 7CB 明るいナチュラルブラウン 鮮やかな髪色6週間続く 医薬部外品",
  "analyzedAt": "2026-05-16T17:42:56.786Z",
  "totalReviews": 51,
  "lowStarCount": 20,
  "highStarCount": 21,
  "avgRating": "3.04",
  "painPoints": {
    "品質": {
      "count": 1,
      "words": [
        "割れ"
      ]
    },
    "耐久": {
      "count": 2,
      "words": [
        "長持ち",
        "1年"
      ]
    },
    "サイズ": {
      "count": 1,
      "words": [
        "合わない"
      ]
    },
    "デザイン": {
      "count": 15,
      "words": [
        "色"
      ]
    },
    "価格": {
      "count": 1,
      "words": [
        "値段"
      ]
    },
    "梱包": {
      "count": 9,
      "words": [
        "箱",
        "破れ",
        "配送"
      ]
    },
    "サポート": {
      "count": 3,
      "words": [
        "返品"
      ]
    },
    "互換": {
      "count": 1,
      "words": [
        "違う"
      ]
    }
  },
  "praisePoints": {
    "満足": {
      "count": 9,
      "words": [
        "良い",
        "満足",
        "おすすめ"
      ]
    },
    "品質": {
      "count": 6,
      "words": [
        "しっかり",
        "ちゃんと"
      ]
    },
    "価値": {
      "count": 2,
      "words": [
        "コスパ",
        "お得"
      ]
    },
    "使いやすさ": {
      "count": 3,
      "words": [
        "使いやすい",
        "手軽"
      ]
    }
  },
  "painMatches": {
    "品質": [
      {
        "idx": 5,
        "hitWord": "割れ",
        "rating": 1,
        "title": "商品管理、製造管理の問題？",
        "body": "届いた商品を開けて中身をとりだすと、チュウブがへこみ、染毛剤を混ぜ合わせるプラスチックの皿が割れていた。個装箱にへこみ等は見当たらなかった。同時配送の別商品には異常はなかった。このことから、配送中の問題ではなく、商品を個装箱に入れる製造時の問題ではないかと疑われる。"
      }
    ],
    "耐久": [
      {
        "idx": 15,
        "hitWord": "1年",
        "rating": 2,
        "title": "ウエラ白髪染め",
        "body": "定期購入を始めて1年足らずですが、手袋が入っていないのが2回目と当たりたくない目玉品です。"
      },
      {
        "idx": 18,
        "hitWord": "長持ち",
        "rating": 2,
        "title": "2週間程度で色落ち",
        "body": "何度もリピート購入しています。カラーリング後72時間はシャンプーを控えたり、できるだけ長持ちさせようと試みてみましたが2週間程度で色落ちしますね。"
      }
    ],
    "サイズ": [
      {
        "idx": 1,
        "hitWord": "合わない",
        "rating": 2,
        "title": "頭皮痛くない",
        "body": "傷みを気にして、無理してウエラ使ってたが、ものすごく色落ち早いことに気付きました。私には合わないようです。全く頭皮は痛くならないけれど。"
      }
    ],
    "説明書": [],
    "におい": [],
    "音": [],
    "使い勝手": [],
    "デザイン": [
      {
        "idx": 1,
        "hitWord": "色",
        "rating": 2,
        "title": "頭皮痛くない",
        "body": "傷みを気にして、無理してウエラ使ってたが、ものすごく色落ち早いことに気付きました。私には合わないようです。全く頭皮は痛くならないけれど。"
      },
      {
        "idx": 2,
        "hitWord": "色",
        "rating": 1,
        "title": "8GMは見本の色と全く違う",
        "body": "赤みを抑えたアッシュ系と思って購入。金金してしまいました、、、8GMは見本の色と全く違い、明るすぎる色になります。見本の写真にはよく見たらAIが生成した画像ですと書かれており、実際に染めた色ではないのか…と納得。本当に残念です。"
      },
      {
        "idx": 3,
        "hitWord": "色",
        "rating": 1,
        "title": "量が少ない",
        "body": "量が少なく色が暗かった。見本と乖離している。付属のオイルで髪が乾かなかったので要らないですね。"
      },
      {
        "idx": 9,
        "hitWord": "色",
        "rating": 1,
        "title": "染まりませんでした",
        "body": "いつもウエラの黄色のパッケージのを使って満足してたのですがクチコミが良かったので、こちらも使ってみようと購入してみましたが、全然仕上がりが良くなくて、残り捨てました。"
      },
      {
        "idx": 12,
        "hitWord": "色",
        "rating": 2,
        "title": "白髪ぞめ特有の赤っぽくなります",
        "body": "染まり方はいいと思う。赤っぽくなるのが嫌でこの色を選んだのに、見事に赤っぽくなった。内側は赤く、そこ以外黒かったら白髪染めしてます、っていうのが強調されて最悪。いやすぎて翌日サロンドプロで染め直した。落ちにくいから色が気にいればよいのでは。"
      },
      {
        "idx": 14,
        "hitWord": "色",
        "rating": 2,
        "title": "今まで使ってきたカラー剤の中で1番色持ちが悪い",
        "body": "白髪染めなら色持ちがいいかと思い使用してみましたが、相性が悪かったのか歴代使用してきたカラー剤の中で1番持ちが悪かったです。お値段そこそこ高めで１週間しか持たないならリピートはなしですね。ウルフカットで横がフェイスラインくらい、後ろが腰くらいの長さの髪で1箱丸々使いました。"
      },
      {
        "idx": 17,
        "hitWord": "色",
        "rating": 2,
        "title": "髪がパサパサ",
        "body": "成分がキツくて髪がパサパサで色むらもひどいです。美容院で染めるのが一番かも。"
      },
      {
        "idx": 18,
        "hitWord": "色",
        "rating": 2,
        "title": "2週間程度で色落ち",
        "body": "何度もリピート購入しています。カラーリング後72時間はシャンプーを控えたり、できるだけ長持ちさせようと試みてみましたが2週間程度で色落ちしますね。"
      },
      {
        "idx": 19,
        "hitWord": "色",
        "rating": 2,
        "title": "色が好き",
        "body": "箱が破れていました。商品に問題ないかと思って使います。"
      }
    ],
    "価格": [
      {
        "idx": 14,
        "hitWord": "値段",
        "rating": 2,
        "title": "今まで使ってきたカラー剤の中で1番色持ちが悪い",
        "body": "白髪染めなら色持ちがいいかと思い使用してみましたが、相性が悪かったのか歴代使用してきたカラー剤の中で1番持ちが悪かったです。お値段そこそこ高めで１週間しか持たないならリピートはなしですね。ウルフカットで横がフェイスラインくらい、後ろが腰くらいの長さの髪で1箱丸々使いました。"
      }
    ],
    "梱包": [
      {
        "idx": 5,
        "hitWord": "箱",
        "rating": 1,
        "title": "商品管理、製造管理の問題？",
        "body": "届いた商品を開けて中身をとりだすと、チュウブがへこみ、染毛剤を混ぜ合わせるプラスチックの皿が割れていた。個装箱にへこみ等は見当たらなかった。同時配送の別商品には異常はなかった。このことから、配送中の問題ではなく、商品を個装箱に入れる製造時の問題ではないかと疑われる。"
      },
      {
        "idx": 6,
        "hitWord": "配送",
        "rating": 1,
        "title": "配達に問題",
        "body": "いつも置き配にしていないのに、勝手に置き配を行なっています。配達業者に指導を徹底してほしいです。商品に問題ないですが、配送に問題がある為、評価を低くしざるを得ません。"
      },
      {
        "idx": 10,
        "hitWord": "箱",
        "rating": 1,
        "title": "ゴミ箱行き",
        "body": "全然白髪が染まりません買って失敗したけど、これで2度と買わないことと分かった為その点良かったです"
      },
      {
        "idx": 14,
        "hitWord": "箱",
        "rating": 2,
        "title": "今まで使ってきたカラー剤の中で1番色持ちが悪い",
        "body": "白髪染めなら色持ちがいいかと思い使用してみましたが、相性が悪かったのか歴代使用してきたカラー剤の中で1番持ちが悪かったです。お値段そこそこ高めで１週間しか持たないならリピートはなしですね。ウルフカットで横がフェイスラインくらい、後ろが腰くらいの長さの髪で1箱丸々使いました。"
      },
      {
        "idx": 19,
        "hitWord": "箱",
        "rating": 2,
        "title": "色が好き",
        "body": "箱が破れていました。商品に問題ないかと思って使います。"
      }
    ],
    "サポート": [
      {
        "idx": 7,
        "hitWord": "返品",
        "rating": 1,
        "title": "損傷品が送られて来たが返品できない",
        "body": "一緒に入っているトリートメントの袋にカッターで切られたような損傷したものが納品された。しかも化粧品なので返品できないとふざけた回答に呆れている。"
      },
      {
        "idx": 11,
        "hitWord": "返品",
        "rating": 1,
        "title": "返品されたものなのか？",
        "body": "開封済みのものが届きました。検品をしていないのでしょうか。"
      }
    ],
    "互換": [
      {
        "idx": 2,
        "hitWord": "違う",
        "rating": 1,
        "title": "8GMは見本の色と全く違う",
        "body": "赤みを抑えたアッシュ系と思って購入。金金してしまいました、、、8GMは見本の色と全く違い、明るすぎる色になります。見本の写真にはよく見たらAIが生成した画像ですと書かれており、実際に染めた色ではないのか…と納得。本当に残念です。"
      }
    ]
  },
  "praiseMatches": {
    "満足": [
      {
        "idx": 1,
        "hitWord": "良い",
        "rating": 4,
        "title": "綺麗に染まる",
        "body": "クリームタイプのため、泡タイプよりも塗るのに時間がかかるが染め上がりや乾燥後の髪のツヤ感は良いです。価格は多少高めかも知れませんが月一なら使い続けても良いかもっていう感じです。"
      },
      {
        "idx": 6,
        "hitWord": "良い",
        "rating": 5,
        "title": "色持ちはいいので結果塗布回数が減る",
        "body": "色持ちが長い、パサつきも感じない、しっとりする、エッセンスが別についているけどこれが良い。匂いもしなくて、ちょっと敏感な私でも使える。クリームタイプの塗布は大変、髪全体より、リタッチとして使ってる。色もたくさんあるので、次はまた違うのを使ってみたい。"
      },
      {
        "idx": 8,
        "hitWord": "良い",
        "rating": 4,
        "title": "色が良い",
        "body": "何度もリピートしています。色持ちが悪く色が抜けると赤みが出て非常に明るくなりやすいタイプなのですが、こちらの商品の8SAという色だと色が抜けてからも赤みが出にくいです。すごく明るくなることもなく気に入っています。ですが、白髪は若干染まりにくいように思います。"
      },
      {
        "idx": 15,
        "hitWord": "満足",
        "rating": 4,
        "title": "コスパ、染まり具合綺麗、おすすめしたい",
        "body": "以前まで頭皮湿疹出来てた私がこのカラー使ってからあまり刺激が少なく頭皮に負担なく染めれて綺麗な仕上がりに満足でいつもリピ買いしてる商品。"
      },
      {
        "idx": 16,
        "hitWord": "良い",
        "rating": 4,
        "title": "初めて利用",
        "body": "今まで使っていた白髪染が廃盤になったので以前から気になっていたこちらを初めて購入。○若干匂いがあるもののそれほど強くはない。○頭皮に刺激や痛みはなくてよかった。○染め終わりのシャンプーの際泡やタオルに色落ちせずびっくり。浴室汚れず良い！×混ぜ辛い×ハケは使いやすいがブラシ部分は使い辛い当初混ぜて塗り始めた時はリピはないなと思いましたが刺激がないのとタオルが汚れないのでこれからも使ってみようかな？と"
      },
      {
        "idx": 17,
        "hitWord": "おすすめ",
        "rating": 5,
        "title": "市販品でここまで染まるとは思わなかった",
        "body": "サロンでグレージュ系に染めていましたが、費用を抑えたくて初めて市販の白髪染めに挑戦しました。8CGのクリスタルグレージュは思っていたよりくすみすぎず、自然なグレージュに仕上がりました。白髪への染まりもムラなくしっかりで、生え際もきれいにカバーできています。クリームタイプで液垂れしにくく、初めてでも塗りやすかったのは助かりました。使い始めて2回目になりますが、色持ちも約6週間という記載通りで思ったよ"
      }
    ],
    "品質": [
      {
        "idx": 3,
        "hitWord": "ちゃんと",
        "rating": 5,
        "title": "ちゃんと白髪が染まります",
        "body": "今まではおしゃれ染めで誤魔化してましたが、ちゃんとした白髪染めを試そうと思い、お値段もお手頃なこちらを購入しました。オイル混ぜるの忘れちゃったけどちゃんと白髪は染まりました。ショートなので半分ぐらい余りました(笑)取っておけるのがいいですね。まだ白髪が部分的なのでリタッチマスカラでもよさそうですが、たまにはこういうのも使って今のうちに慣れておこうと思います(笑)"
      },
      {
        "idx": 17,
        "hitWord": "しっかり",
        "rating": 5,
        "title": "市販品でここまで染まるとは思わなかった",
        "body": "サロンでグレージュ系に染めていましたが、費用を抑えたくて初めて市販の白髪染めに挑戦しました。8CGのクリスタルグレージュは思っていたよりくすみすぎず、自然なグレージュに仕上がりました。白髪への染まりもムラなくしっかりで、生え際もきれいにカバーできています。クリームタイプで液垂れしにくく、初めてでも塗りやすかったのは助かりました。使い始めて2回目になりますが、色持ちも約6週間という記載通りで思ったよ"
      }
    ],
    "価値": [
      {
        "idx": 12,
        "hitWord": "お得",
        "rating": 4,
        "title": "近くの店舗になかったのですが",
        "body": "こちらで見つけました。タイミングがよくお得に購入できてよかったです。染まりますが、落ちるのが少し早い気が…髪質にもよるのかもしれません。"
      },
      {
        "idx": 15,
        "hitWord": "コスパ",
        "rating": 4,
        "title": "コスパ、染まり具合綺麗、おすすめしたい",
        "body": "以前まで頭皮湿疹出来てた私がこのカラー使ってからあまり刺激が少なく頭皮に負担なく染めれて綺麗な仕上がりに満足でいつもリピ買いしてる商品。"
      }
    ],
    "使いやすさ": [
      {
        "idx": 16,
        "hitWord": "使いやすい",
        "rating": 4,
        "title": "初めて利用",
        "body": "今まで使っていた白髪染が廃盤になったので以前から気になっていたこちらを初めて購入。○若干匂いがあるもののそれほど強くはない。○頭皮に刺激や痛みはなくてよかった。○染め終わりのシャンプーの際泡やタオルに色落ちせずびっくり。浴室汚れず良い！×混ぜ辛い×ハケは使いやすいがブラシ部分は使い辛い当初混ぜて塗り始めた時はリピはないなと思いましたが刺激がないのとタオルが汚れないのでこれからも使ってみようかな？と"
      },
      {
        "idx": 17,
        "hitWord": "手軽",
        "rating": 5,
        "title": "市販品でここまで染まるとは思わなかった",
        "body": "サロンでグレージュ系に染めていましたが、費用を抑えたくて初めて市販の白髪染めに挑戦しました。8CGのクリスタルグレージュは思っていたよりくすみすぎず、自然なグレージュに仕上がりました。白髪への染まりもムラなくしっかりで、生え際もきれいにカバーできています。クリームタイプで液垂れしにくく、初めてでも塗りやすかったのは助かりました。使い始めて2回目になりますが、色持ちも約6週間という記載通りで思ったよ"
      },
      {
        "idx": 20,
        "hitWord": "使いやすい",
        "rating": 5,
        "title": "使いやすい",
        "body": "自然な色ですぐ馴染むのでリピ"
      }
    ]
  },
  "topNgramsLow": [
    {
      "gram": "ました",
      "count": 14
    },
    {
      "gram": "かった",
      "count": 10
    },
    {
      "gram": "染まり",
      "count": 6
    },
    {
      "gram": "使って",
      "count": 5
    },
    {
      "gram": "ってい",
      "count": 5
    },
    {
      "gram": "いまし",
      "count": 5
    },
    {
      "gram": "したが",
      "count": 5
    },
    {
      "gram": "ったの",
      "count": 5
    },
    {
      "gram": "たので",
      "count": 5
    },
    {
      "gram": "ないの",
      "count": 5
    },
    {
      "gram": "ではな",
      "count": 5
    },
    {
      "gram": "ません",
      "count": 5
    },
    {
      "gram": "ていま",
      "count": 4
    },
    {
      "gram": "てみま",
      "count": 4
    },
    {
      "gram": "みまし",
      "count": 4
    }
  ],
  "topNgramsHigh": [
    {
      "gram": "ました",
      "count": 16
    },
    {
      "gram": "染まり",
      "count": 9
    },
    {
      "gram": "使って",
      "count": 8
    },
    {
      "gram": "います",
      "count": 8
    },
    {
      "gram": "かった",
      "count": 8
    },
    {
      "gram": "ってい",
      "count": 7
    },
    {
      "gram": "ていま",
      "count": 7
    },
    {
      "gram": "白髪染",
      "count": 6
    },
    {
      "gram": "ります",
      "count": 6
    },
    {
      "gram": "染まる",
      "count": 6
    },
    {
      "gram": "りまし",
      "count": 6
    },
    {
      "gram": "ですが",
      "count": 6
    },
    {
      "gram": "髪染め",
      "count": 5
    },
    {
      "gram": "まりま",
      "count": 5
    },
    {
      "gram": "タイプ",
      "count": 5
    }
  ]
}