{
  "asin": "B081GLYKCD",
  "productTitle": "タニタ 手首式血圧計 ホワイト BP-A11",
  "scrapedAt": "2026-05-16T16:19:31.073Z",
  "reviewCount": 51,
  "reviews": [
    {
      "rating": 5,
      "title": "コンパクトに収納できて、使いやすいです。",
      "body": "使いやすく、履歴データも簡単に確認ができます。不整脈も感知、通知してくれたので、病院に行くこともできました。",
      "date": "2026年4月28日に日本でレビュー済み",
      "verified": true,
      "source": "役立った順"
    },
    {
      "rating": 4,
      "title": "軽量コンパクトで使いやすい",
      "body": "（良い点）コンパクトで持ち運びに便利使い方が簡単で気軽に測定できるデザインが良くチープさは全く無い電池の持ちが良い画面表示の文字が大きくて見やすい（悪い点）複数回測定した場合結果に多少バラツキありマジックテープ部分が少し使いづらい画面上部の日付時刻が影に隠れてしまい見えにくい（総評）価格も安くて持ち運びやすいですこれならば自分専用として所持しても良い病院などで使われる上腕タイプは測定時の姿勢が強制されるので正確性があるのだと思うこの商品も測定器と心臓の高さを同じにして使えば正確な結果が期待できる毎日の生活で自分の血圧を気にかけるようになっただけでも買う価値は十分にあったこれと同じような商品が数多くあるがやはりこういった大事なことを計測する目的の場合にはタニタのような信頼ある有名メーカーのモノを買うべき",
      "date": "2026年1月17日に日本でレビュー済み",
      "verified": true,
      "source": "役立った順"
    },
    {
      "rating": 3,
      "title": "測定精度の安定性は？",
      "body": "お手軽に持ち運びでき使い勝手は良いですが、ちょっと測定の状況変化により数値のバラつきが目立ちます。",
      "date": "2026年3月20日に日本でレビュー済み",
      "verified": true,
      "source": "役立った順"
    },
    {
      "rating": 5,
      "title": "信頼のタニタで簡単測定",
      "body": "タニタのため、信用して購入。コンパクト、軽量、操作もとても分かりやすい。毎日血圧を測る親に送る。時々自分も測ってみるが、若干高めに数値が出るような気もしてならない。体勢や環境の違いからか。とにかく急ぎで一つ必要、というなら値段ともども文句なしだ。",
      "date": "2026年5月6日に日本でレビュー済み",
      "verified": true,
      "source": "役立った順"
    },
    {
      "rating": 5,
      "title": "楽に使える",
      "body": "安価で手頃、更に正確。目安としての安心感はあります。使い方も簡単で取扱説明書も丁寧でオススメです。",
      "date": "2026年5月10日に日本でレビュー済み",
      "verified": true,
      "source": "役立った順"
    },
    {
      "rating": 4,
      "title": "測定は簡単、日時設定は超超超難関",
      "body": "昔の腕にグルって巻くタイプに比べて測定時間が短くなったので感心しました。取り付けも簡単、技術の進歩はすごい！ただし日付の設定が超難しい。文字は小さいし操作ボタンは限られているし、体調の悪い今の状況では設定は無理。もっと簡単になりませんかね。それで減点１点",
      "date": "2026年5月14日に日本でレビュー済み",
      "verified": true,
      "source": "役立った順"
    },
    {
      "rating": 5,
      "title": "使いやすい！",
      "body": "他社の手首タイプのマジックテープが弱くなり使えなくなったので、こちらを購入しました。テープもしっかりしていて長持ちしそうです。収納ケースもコンパクトで持ち運びにも良いです。おすすめします！",
      "date": "2026年5月9日に日本でレビュー済み",
      "verified": true,
      "source": "役立った順"
    },
    {
      "rating": 4,
      "title": "さすがタニタさん",
      "body": "正味の腕のタイプとは少し値に差がありますが、まぁ手首やからちゃいますよね。見やすいし、使いやすいし、値はこれ基準に考えればええだけなので便利です。",
      "date": "2026年4月29日に日本でレビュー済み",
      "verified": true,
      "source": "役立った順"
    },
    {
      "rating": 4,
      "title": "スイッチの位置が気になる",
      "body": "簡易的に使用するものと理解して購入しましたが、如何せんスイッチの位置が私には合わず、何度か触ってしまい動作が始まる事が。簡単操作出来るので、ここだけ残念。",
      "date": "2026年5月3日に日本でレビュー済み",
      "verified": true,
      "source": "役立った順"
    },
    {
      "rating": 4,
      "title": "まずまず",
      "body": "若干血圧高めにでる",
      "date": "2026年5月2日に日本でレビュー済み",
      "verified": true,
      "source": "役立った順"
    },
    {
      "rating": 5,
      "title": "安心、安心です",
      "body": "タニタは裏切らない",
      "date": "2026年5月14日に日本でレビュー済み",
      "verified": true,
      "source": "新しい順"
    },
    {
      "rating": 1,
      "title": "使えたの1ヶ月だけでした",
      "body": "4月6日に母親にプレゼントしました。その後現在電池替えても付かない。使い物にならない。最悪",
      "date": "2026年5月13日に日本でレビュー済み",
      "verified": true,
      "source": "新しい順"
    },
    {
      "rating": 5,
      "title": "毎日使用しています。",
      "body": "毎日問題なく作動しています。",
      "date": "2026年5月10日に日本でレビュー済み",
      "verified": true,
      "source": "新しい順"
    },
    {
      "rating": 5,
      "title": "携帯性に優れたタニタの商品",
      "body": "携帯性と使いやすさで選びました。さすがタニタ",
      "date": "2026年5月8日に日本でレビュー済み",
      "verified": true,
      "source": "新しい順"
    },
    {
      "rating": 5,
      "title": "簡単コンパクト",
      "body": "良いです",
      "date": "2026年5月8日に日本でレビュー済み",
      "verified": true,
      "source": "新しい順"
    },
    {
      "rating": 5,
      "title": "良かった",
      "body": "ちゃんと使える誤差もすくない。",
      "date": "2026年5月7日に日本でレビュー済み",
      "verified": true,
      "source": "新しい順"
    },
    {
      "rating": 5,
      "title": "母の日ギフトにも良いと思う",
      "body": "母の健康管理用に買いました、簡単に使えて喜んでくれました",
      "date": "2026年5月7日に日本でレビュー済み",
      "verified": true,
      "source": "新しい順"
    },
    {
      "rating": 1,
      "title": "がっかり",
      "body": "4ヶ月で壊れた電池変えても動かず",
      "date": "2026年5月4日に日本でレビュー済み",
      "verified": true,
      "source": "★1"
    },
    {
      "rating": 1,
      "title": "測定結果が信頼できない",
      "body": "測定結果が低すぎる。カフの位置、腕の位置、高さを色々試行錯誤するが20〜30ほど低く結果が表示される。著しく信頼性が劣る野手結果が信用できない。変品ができないようでどうにもならない。",
      "date": "2026年4月27日に日本でレビュー済み",
      "verified": true,
      "source": "★1"
    },
    {
      "rating": 1,
      "title": "だめです",
      "body": "もう壊れました。実店舗で買いましょう。総じてタニタのこのタイプは、本当に測れていたのか疑問です。",
      "date": "2026年4月25日に日本でレビュー済み",
      "verified": true,
      "source": "★1"
    },
    {
      "rating": 1,
      "title": "信頼性に疑問しかない",
      "body": "異常に高い数値がでる。説明通りに使っても何度やっても。信頼性無し。病院ですぐ測ってもらった費用も無駄になった。血圧は正常だった。",
      "date": "2026年4月27日に日本でレビュー済み",
      "verified": true,
      "source": "★1"
    },
    {
      "rating": 1,
      "title": "安いけど覚悟しと買うことをお勧めします",
      "body": "安物買いの銭失い血圧高く医者から測るよう勧められ渋々買ったもののまー毎回バラバラor低血圧気味有名メーカーだから安いし良いかと思いましたが、、、返金しようかとも思ったけどメンドイのでレビューだけ注意喚起含め腹たったので、、、追記もしかしたら他の方には良い品かもしれないので買ってみても良いかも値段はかなり安いので自分には合わなかった",
      "date": "2026年4月21日に日本でレビュー済み",
      "verified": true,
      "source": "★1"
    },
    {
      "rating": 1,
      "title": "不良品かなと",
      "body": "数値がなにかおかしい",
      "date": "2026年4月29日に日本でレビュー済み",
      "verified": true,
      "source": "★1"
    },
    {
      "rating": 1,
      "title": "値段相応",
      "body": "壊れました",
      "date": "2026年4月26日に日本でレビュー済み",
      "verified": true,
      "source": "★1"
    },
    {
      "rating": 1,
      "title": "返品できない",
      "body": "買ったその日に電池のカバーが閉まらなくなり使えなくなりました。返品に応じてくれませんでした。",
      "date": "2026年4月25日に日本でレビュー済み",
      "verified": true,
      "source": "★1"
    },
    {
      "rating": 1,
      "title": "何年待っのか?",
      "body": "それなりのモノ壊れるのは早そうだ",
      "date": "2026年4月25日に日本でレビュー済み",
      "verified": true,
      "source": "★1"
    },
    {
      "rating": 2,
      "title": "膨張した電池で電池交換に無理がありました",
      "body": "１ヶ月ほど使いました時間を大まかに決めて記録していくと傾向が見えてくるのでおすすめですで、１ヶ月使って電池が切れました交換しようとして単4が2本入っていたので取り出そうとしたら片方だけ出てきません！もう交換してもらおうかと思ってAmazonで見ると直接タニタから送られてきた物はAmazonが関与しないとありましたもうダメだと思ってネジを外して外から電池に届く隙間を見つけたので細長い物を突っ込んで無理やり出しました…出てきた電池が削れていました膨張していたようですいつからこの電池は入っていたんでしょうかおかげで電池の蓋で手を切りました医療機器で怪我をするとは思いませんでした",
      "date": "2026年5月1日に日本でレビュー済み",
      "verified": true,
      "source": "★2"
    },
    {
      "rating": 2,
      "title": "液晶が弱すぎる",
      "body": "2年で液晶が表示しない、それまでもマジックテープを止める時など胸に軽く当てただけで液晶がバグる",
      "date": "2026年4月14日に日本でレビュー済み",
      "verified": true,
      "source": "★2"
    },
    {
      "rating": 2,
      "title": "手首タイプは不正確らしい",
      "body": "これで毎日測って内科医に見せたところ数字が全く信用ならないとのこと。確かに病院の血圧計で測るより10〜20ギャップが出ます。手首でなく腕で測るものでないと駄目だそうです。",
      "date": "2026年4月15日に日本でレビュー済み",
      "verified": true,
      "source": "★2"
    },
    {
      "rating": 2,
      "title": "正確？",
      "body": "４回連続で計測しても129の最高血圧が同数値だったり、翌日も129が何度も出て正しく計測されてるいのか疑問。",
      "date": "2026年4月9日に日本でレビュー済み",
      "verified": true,
      "source": "★2"
    },
    {
      "rating": 2,
      "title": "正確？",
      "body": "タニタさんはキッチン秤とか持ってるし信頼できるメーカーさんだと思うけど、数ヶ月前かかりつけ医で180代の血圧になったので薬を処方してもらい、自宅でも定期的な測定は必要とのことで購入したのだけれど、いつ測っても最低60前後、最高100前後　と、いたって普通(筋トレ直後でも120)であるのに　何故か医者で測るといつも上が150を超える。薬飲んでいてそれだから、もう少し奮発して「高級な血圧計」再購入を検討中",
      "date": "2026年3月28日に日本でレビュー済み",
      "verified": true,
      "source": "★2"
    },
    {
      "rating": 2,
      "title": "値段で決めない方がよい",
      "body": "他の血圧計を使用していましたが、壊れたので、一番安いこちらを買いました、まずは、３回連続して測ると　毎回１０くらい変動して、あまりあてになりません。前に使用していた数個の物は、変動も大きくて５くらいだったです。それとも男性ですがも手首が細目で平べったい形の手首ですと手首に撒く形状がうまく合わず、途中再吸気することが多く、測定が高めにでます。毎日使うものとしては、総合的に、使いにくい血圧計です。他社の物を買いなおし検知中。",
      "date": "2026年3月12日に日本でレビュー済み",
      "verified": true,
      "source": "★2"
    },
    {
      "rating": 2,
      "title": "故障？",
      "body": "エラー表示が頻発にでる",
      "date": "2026年2月8日に日本でレビュー済み",
      "verified": true,
      "source": "★2"
    },
    {
      "rating": 2,
      "title": "平均値を算出と書いてあるが...",
      "body": "う〜ん...毎回使う度に、血圧変動差が大きく、連続で計っても数値の開きが大きくて、本当の数値は計れるのだろうかと不安になってます。この手首に巻く仕様は、精密に計れないのかもしれないです。",
      "date": "2025年12月15日に日本でレビュー済み",
      "verified": true,
      "source": "★2"
    },
    {
      "rating": 2,
      "title": "自分はいらない",
      "body": "血圧計三つ持ってますが、これは上も下もかなり高めに出ます",
      "date": "2025年12月14日に日本でレビュー済み",
      "verified": true,
      "source": "★2"
    },
    {
      "rating": 2,
      "title": "購入後3年で故障",
      "body": "2022年9月に購入使用後3年で液晶表示が不良になりモーター動作もしなくなりました。耐久性に疑問を感じました。安いので仕方がないと諦め、今はシチズンの血圧計を使ってます。",
      "date": "2025年12月8日に日本でレビュー済み",
      "verified": true,
      "source": "★2"
    },
    {
      "rating": 3,
      "title": "あまり精度は高くない！",
      "body": "日本のメーカーだから信用していたが………あまり精度は良くない！値段相応！",
      "date": "2026年5月5日に日本でレビュー済み",
      "verified": true,
      "source": "★3"
    },
    {
      "rating": 3,
      "title": "手首式は面倒",
      "body": "手首式を購入したのですが、腕を心臓辺りに置かないと正常に計れません。やはり一般的な血圧計の方が良かったかな。",
      "date": "2026年4月28日に日本でレビュー済み",
      "verified": true,
      "source": "★3"
    },
    {
      "rating": 3,
      "title": "落とさないように（簡単に壊れます）",
      "body": "液晶が簡単に壊れます。使い勝手は悪くなかったのですが、テーブルから落としただけで、血圧計の液晶が表示されなくなりました。こんなにも簡単に壊れるなんて。",
      "date": "2026年4月27日に日本でレビュー済み",
      "verified": true,
      "source": "★3"
    },
    {
      "rating": 3,
      "title": "同じタニタでも差がある",
      "body": "昨日、タニタの温湿度計を買ったら、他のタニタの温湿度計と比べ、かなり温度も湿度も差がありました。体重計もタニタのインナースキャンデュアルと安いタニタの体重計で、1.3キロも差がありました。オムロンの腕巻き式と、こちらのタニタの手首式を比べてみたら、思った以上に差がありました。どっちが正しいのかわかりませんが、タニタブランドを信じていたのですが、温湿度計も体重計も同じタニタなのに、かなり差があるので、こちらよりオムロンのほうが正しいのではないかと思いました。",
      "date": "2026年4月24日に日本でレビュー済み",
      "verified": true,
      "source": "★3"
    },
    {
      "rating": 3,
      "title": "毎回血圧が違う",
      "body": "すぐに計り直したら違う数値が出る。使えない。",
      "date": "2026年4月20日に日本でレビュー済み",
      "verified": true,
      "source": "★3"
    },
    {
      "rating": 3,
      "title": "残念なレベル",
      "body": "腕の締め付けが解けてしまいます。ちょっと改善して欲しいです。",
      "date": "2026年4月14日に日本でレビュー済み",
      "verified": true,
      "source": "★3"
    },
    {
      "rating": 3,
      "title": "お安く買えましたが",
      "body": "手軽でいいけど、手首式は高めに出るようですね。正しい計測方法で測っています。",
      "date": "2026年4月14日に日本でレビュー済み",
      "verified": true,
      "source": "★3"
    },
    {
      "rating": 3,
      "title": "何故でしょう？",
      "body": "概ね気に入りましたが先日電池交換しようと電池を取り出そうとしたら片方がなかなか出てこなくてペンチで力一杯引っ張ってやっと出せました。これって不良品ではないでしょうか？面倒なので何もしてませんが次の電池交換が億劫に感じます",
      "date": "2026年4月9日に日本でレビュー済み",
      "verified": true,
      "source": "★3"
    },
    {
      "rating": 3,
      "title": "価格では測れません",
      "body": "値段の割には上質ですが設定ボタンがデカすぎて、押す気ないのに触ってしまい面倒です心臓の位置と高さ変わるとやり直しになりお気軽に出来ません",
      "date": "2026年4月4日に日本でレビュー済み",
      "verified": true,
      "source": "★3"
    },
    {
      "rating": 4,
      "title": "良い",
      "body": "良い。安心のタニタです。",
      "date": "2026年4月24日に日本でレビュー済み",
      "verified": true,
      "source": "★4"
    },
    {
      "rating": 4,
      "title": "皆ではかろう。",
      "body": "いいものです。",
      "date": "2026年4月17日に日本でレビュー済み",
      "verified": true,
      "source": "★4"
    },
    {
      "rating": 4,
      "title": "こんなもんでしょう…",
      "body": "手首型なので、手首の高低で計測値にかなりの開きが出ます…。胸より高いと低い数値、胸より低いと高い数値になります…。上腕型と比べて±10〜くらいの差と思えば大した問題ではありません…。",
      "date": "2026年4月17日に日本でレビュー済み",
      "verified": true,
      "source": "★4"
    },
    {
      "rating": 4,
      "title": "使用時の理解が重要",
      "body": "手首測定型の商品ですので、測定時の手の位置や体勢が悪いと良くない数値(間違った数値)が出ますので、この場合に逆に不安な気持ちになってしまうことがあります。ポイントは、\"手首に設置した測定器が自分の上腕(力こぶ)と同じ高さになりように肘をVの字に曲げる\"という理解です。",
      "date": "2026年4月14日に日本でレビュー済み",
      "verified": true,
      "source": "★4"
    },
    {
      "rating": 4,
      "title": "毎日使ってます",
      "body": "手首で簡単に計測出来て良いです(*^^*)",
      "date": "2026年3月30日に日本でレビュー済み",
      "verified": true,
      "source": "★4"
    },
    {
      "rating": 5,
      "title": "買うのを迷ってるのであれば、こちらのショップがお薦めです！",
      "body": "電池まで付けてくれていて親切でした。設定も操作も簡単です。また利用したいと思えるショップでした。",
      "date": "2026年5月6日に日本でレビュー済み",
      "verified": true,
      "source": "★5"
    }
  ]
}