{
  "asin": "B0C9Q25RGB",
  "productTitle": null,
  "analyzedAt": "2026-05-16T16:23:26.585Z",
  "totalReviews": 10,
  "lowStarCount": 1,
  "highStarCount": 9,
  "avgRating": "4.60",
  "painPoints": {
    "デザイン": {
      "count": 1,
      "words": [
        "色"
      ]
    },
    "サポート": {
      "count": 1,
      "words": [
        "返品"
      ]
    }
  },
  "praisePoints": {
    "満足": {
      "count": 5,
      "words": [
        "良い"
      ]
    },
    "価値": {
      "count": 1,
      "words": [
        "買って良かった"
      ]
    }
  },
  "painMatches": {
    "品質": [],
    "耐久": [],
    "サイズ": [],
    "説明書": [],
    "におい": [],
    "音": [],
    "使い勝手": [],
    "デザイン": [
      {
        "idx": 0,
        "hitWord": "色",
        "rating": 2,
        "title": "色味が､､",
        "body": "ダークグレーを購入しましたが、届いた商品を開封するとグレー？思っていたよりかなり薄いグレーでダークグレーが欲しかったのでちょっとショックでした。返品の送料が自己負担になるので替え用として使用しようかと思います。"
      }
    ],
    "価格": [],
    "梱包": [],
    "サポート": [
      {
        "idx": 0,
        "hitWord": "返品",
        "rating": 2,
        "title": "色味が､､",
        "body": "ダークグレーを購入しましたが、届いた商品を開封するとグレー？思っていたよりかなり薄いグレーでダークグレーが欲しかったのでちょっとショックでした。返品の送料が自己負担になるので替え用として使用しようかと思います。"
      }
    ],
    "互換": []
  },
  "praiseMatches": {
    "満足": [
      {
        "idx": 0,
        "hitWord": "良い",
        "rating": 5,
        "title": "リピートします",
        "body": "肌ざわりが やわらかくて良いです。"
      },
      {
        "idx": 4,
        "hitWord": "良い",
        "rating": 5,
        "title": "買って良かった",
        "body": "先日購入したマットレスソファーに使う為に購入しました。写真通りの良い色です。"
      },
      {
        "idx": 7,
        "hitWord": "良い",
        "rating": 5,
        "title": "気持ち良い肌触り",
        "body": "リピで買いました。肌触りが良い商品"
      },
      {
        "idx": 8,
        "hitWord": "良い",
        "rating": 5,
        "title": "質感が良い",
        "body": "吸湿速乾タイプなので、寝ている間のムレ感も少ないです。これからの季節でも気持ちよく使えそうです。夏はさらっと、冬も冷たすぎないちょうどいい質感です。"
      }
    ],
    "品質": [],
    "価値": [
      {
        "idx": 4,
        "hitWord": "買って良かった",
        "rating": 5,
        "title": "買って良かった",
        "body": "先日購入したマットレスソファーに使う為に購入しました。写真通りの良い色です。"
      }
    ],
    "使いやすさ": []
  },
  "topNgramsLow": [
    {
      "gram": "グレー",
      "count": 4
    },
    {
      "gram": "ダーク",
      "count": 2
    },
    {
      "gram": "ークグ",
      "count": 2
    },
    {
      "gram": "クグレ",
      "count": 2
    }
  ],
  "topNgramsHigh": [
    {
      "gram": "肌触り",
      "count": 4
    },
    {
      "gram": "いです",
      "count": 3
    },
    {
      "gram": "ました",
      "count": 3
    },
    {
      "gram": "触りが",
      "count": 2
    },
    {
      "gram": "つ星の",
      "count": 2
    },
    {
      "gram": "星のう",
      "count": 2
    },
    {
      "gram": "のうち",
      "count": 2
    },
    {
      "gram": "購入し",
      "count": 2
    },
    {
      "gram": "気持ち",
      "count": 2
    },
    {
      "gram": "が良い",
      "count": 2
    }
  ]
}