{
  "asin": "B0C99CHP4G",
  "productTitle": "クモリ(Kumori) 掛け布団カバー シングル 洗いざらし 吸湿速乾 素肌にやさしい 柔らかい しっとり ピーチスキン シワ加工 丸洗いOK オールシーズン 布団カバー 掛ふとんカバー (シングル・150X210cm ライトグレー)",
  "analyzedAt": "2026-05-16T16:23:26.484Z",
  "totalReviews": 10,
  "lowStarCount": 0,
  "highStarCount": 10,
  "avgRating": "4.00",
  "painPoints": {},
  "praisePoints": {
    "満足": {
      "count": 5,
      "words": [
        "良い",
        "満足",
        "気に入っ"
      ]
    },
    "価値": {
      "count": 1,
      "words": [
        "コスパ"
      ]
    },
    "使いやすさ": {
      "count": 1,
      "words": [
        "簡単"
      ]
    }
  },
  "painMatches": {
    "品質": [],
    "耐久": [],
    "サイズ": [],
    "説明書": [],
    "におい": [],
    "音": [],
    "使い勝手": [],
    "デザイン": [],
    "価格": [],
    "梱包": [],
    "サポート": [],
    "互換": []
  },
  "praiseMatches": {
    "満足": [
      {
        "idx": 2,
        "hitWord": "満足",
        "rating": 4,
        "title": "ガサガサしていない肌触り",
        "body": "ポリエステル100%の肌触りと、こちらの色が好きなので大変満足しています。そのうち枕カバーも揃えたいです。"
      },
      {
        "idx": 4,
        "hitWord": "良い",
        "rating": 4,
        "title": "肌触りも良いです",
        "body": "コスパがいいです"
      },
      {
        "idx": 5,
        "hitWord": "気に入っ",
        "rating": 4,
        "title": "気に入ってます。",
        "body": "肌触りが良く気に入ってます。"
      },
      {
        "idx": 7,
        "hitWord": "良い",
        "rating": 4,
        "title": "肌触りが良い",
        "body": "アイボリーを買いましたが、濃い感じの色合いでした。思ってた感じと少し違いましたが、肌触りがいいし、部屋も明るく感じるので買ってよかったです。色違いも欲しいぐらいです布団を止める所が紐で少し手間がかかります。チャックが2個付いているので、ちょっとカチャカチャします。"
      }
    ],
    "品質": [],
    "価値": [
      {
        "idx": 4,
        "hitWord": "コスパ",
        "rating": 4,
        "title": "肌触りも良いです",
        "body": "コスパがいいです"
      }
    ],
    "使いやすさ": [
      {
        "idx": 1,
        "hitWord": "簡単",
        "rating": 4,
        "title": "このお値段でこの品質！",
        "body": "このお値段でこの品質は買って間違いなしレベル。肌触りもなめらかで気に入りました。まだ数週間しか使用していないため、耐久性はわかりませんがリーズナブルなため買い替えも負担にならないのもポイントが高いです。一つ言うとしたら、少しズレやすい気がするので四隅にポケットのような隙間が空いていたら簡単に直せるのであったらいいな！と思いました。でも、そんなものはなくても充分買う価値はあります！"
      }
    ]
  },
  "topNgramsLow": [],
  "topNgramsHigh": [
    {
      "gram": "肌触り",
      "count": 10
    },
    {
      "gram": "カバー",
      "count": 7
    },
    {
      "gram": "いです",
      "count": 7
    },
    {
      "gram": "ました",
      "count": 6
    },
    {
      "gram": "がいい",
      "count": 5
    },
    {
      "gram": "るので",
      "count": 5
    },
    {
      "gram": "触りが",
      "count": 5
    },
    {
      "gram": "りがい",
      "count": 4
    },
    {
      "gram": "気に入",
      "count": 4
    },
    {
      "gram": "してい",
      "count": 4
    },
    {
      "gram": "いまし",
      "count": 4
    },
    {
      "gram": "ていま",
      "count": 3
    },
    {
      "gram": "います",
      "count": 3
    },
    {
      "gram": "てます",
      "count": 3
    },
    {
      "gram": "ります",
      "count": 3
    }
  ]
}