{
  "asin": "B0DLGHTXKK",
  "productTitle": "カードセイバー カードセーバー 作業用カードスリーブ PSA鑑定 提出用 1 ポケカ (カードセイバー200枚のみ)",
  "analyzedAt": "2026-05-16T20:40:11.264Z",
  "totalReviews": 30,
  "lowStarCount": 7,
  "highStarCount": 19,
  "avgRating": "3.53",
  "painPoints": {
    "品質": {
      "count": 6,
      "words": [
        "不良",
        "すぐ",
        "破損"
      ]
    },
    "説明書": {
      "count": 1,
      "words": [
        "わからない"
      ]
    },
    "価格": {
      "count": 2,
      "words": [
        "高い",
        "コスパ"
      ]
    }
  },
  "praisePoints": {
    "満足": {
      "count": 7,
      "words": [
        "良い",
        "素晴らしい",
        "満足"
      ]
    },
    "品質": {
      "count": 6,
      "words": [
        "しっかり",
        "ちゃんと",
        "安心"
      ]
    },
    "価値": {
      "count": 3,
      "words": [
        "コスパ"
      ]
    },
    "使いやすさ": {
      "count": 6,
      "words": [
        "使いやすい",
        "簡単"
      ]
    }
  },
  "painMatches": {
    "品質": [
      {
        "idx": 0,
        "hitWord": "すぐ",
        "rating": 1,
        "title": "まあまあかなぁ、、、",
        "body": "コスパはそこそこよし！ただ、到着後に中を確認したら割れ・破損が数枚あり、使えなかったのがあり残念でした、、、また、エッジのバリが結構すごく、ギザギザで指を怪我しましたので使う場合は慎重に取り扱うことをお勧めします！人気なのか、最近すぐに購入できず予約注文の頻度が多い気がするので安定供給に期待したいです。"
      },
      {
        "idx": 2,
        "hitWord": "不良",
        "rating": 1,
        "title": "不良品",
        "body": "50枚中、13枚が割れていて4枚は完全に欠けていました。最悪の商品です。"
      },
      {
        "idx": 6,
        "hitWord": "不良",
        "rating": 2,
        "title": "パッケージ不良",
        "body": "見ているとり開いている。100枚ちゃんと入っているのが不要。"
      }
    ],
    "耐久": [],
    "サイズ": [],
    "説明書": [
      {
        "idx": 5,
        "hitWord": "わからない",
        "rating": 1,
        "title": "接着面のエッジがきつい",
        "body": "材質が硬めのせいか、接着面のエッジ(バリ？)がきつい。見た感じはほとんどわからないが、触っていて、すごく指に引っかかる。半分ぐらいは、引っ掛かりが強く、カードを傷つけないか心配。少し高いがPSA社が推奨する商品を選べばよかった。"
      }
    ],
    "におい": [],
    "音": [],
    "使い勝手": [],
    "デザイン": [],
    "価格": [
      {
        "idx": 0,
        "hitWord": "コスパ",
        "rating": 1,
        "title": "まあまあかなぁ、、、",
        "body": "コスパはそこそこよし！ただ、到着後に中を確認したら割れ・破損が数枚あり、使えなかったのがあり残念でした、、、また、エッジのバリが結構すごく、ギザギザで指を怪我しましたので使う場合は慎重に取り扱うことをお勧めします！人気なのか、最近すぐに購入できず予約注文の頻度が多い気がするので安定供給に期待したいです。"
      },
      {
        "idx": 5,
        "hitWord": "高い",
        "rating": 1,
        "title": "接着面のエッジがきつい",
        "body": "材質が硬めのせいか、接着面のエッジ(バリ？)がきつい。見た感じはほとんどわからないが、触っていて、すごく指に引っかかる。半分ぐらいは、引っ掛かりが強く、カードを傷つけないか心配。少し高いがPSA社が推奨する商品を選べばよかった。"
      }
    ],
    "梱包": [],
    "サポート": [],
    "互換": []
  },
  "praiseMatches": {
    "満足": [
      {
        "idx": 3,
        "hitWord": "良い",
        "rating": 5,
        "title": "期待どおりです。",
        "body": "ちょうど良い。"
      },
      {
        "idx": 11,
        "hitWord": "良い",
        "rating": 4,
        "title": "コスパ良し",
        "body": "しっかりしていて良い感じです。コスパとても良いです！"
      },
      {
        "idx": 12,
        "hitWord": "素晴らしい",
        "rating": 4,
        "title": "また買いたい",
        "body": "素晴らしい商品、もっと安かったらほんとうにありがたいです。カードもスルリとはいって、出し入れしても傷も全然つかないまた買うと思います。"
      },
      {
        "idx": 13,
        "hitWord": "良い",
        "rating": 4,
        "title": "口の両サイドに開けやすいよう段差加工アリ",
        "body": "PSA用に安めのもので良いのがないか探していてこちらを購入安めなのでちょっと不安だったのですがしっかりと入り口部分にカードが出し入れしやすくなる段差をつける加工がされており閉開が楽な仕様。低価格帯でこれがしてあるのはとても良いですね柔らかすぎず固すぎずほどよい具合なのでちゃんと保護の役割を果たしてくれそうです"
      },
      {
        "idx": 14,
        "hitWord": "満足",
        "rating": 4,
        "title": "鑑定時必須",
        "body": "鑑定時に必要なアイテムが全部そろっています。コスパも良くて満足です。"
      }
    ],
    "品質": [
      {
        "idx": 11,
        "hitWord": "しっかり",
        "rating": 4,
        "title": "コスパ良し",
        "body": "しっかりしていて良い感じです。コスパとても良いです！"
      },
      {
        "idx": 13,
        "hitWord": "しっかり",
        "rating": 4,
        "title": "口の両サイドに開けやすいよう段差加工アリ",
        "body": "PSA用に安めのもので良いのがないか探していてこちらを購入安めなのでちょっと不安だったのですがしっかりと入り口部分にカードが出し入れしやすくなる段差をつける加工がされており閉開が楽な仕様。低価格帯でこれがしてあるのはとても良いですね柔らかすぎず固すぎずほどよい具合なのでちゃんと保護の役割を果たしてくれそうです"
      },
      {
        "idx": 15,
        "hitWord": "安心",
        "rating": 4,
        "title": "高品質で安心して使えます",
        "body": "スリーブ100枚・カードセイバー50枚のセットです。PSA鑑定対応とのことで、サイズもちょうど良く出し入れしやすいです。保護性能とか耐久性はまだ判りませんが、好きな人達が作っているんだろうなぁと分かる製品なので品質も信頼が置けそうです。"
      },
      {
        "idx": 16,
        "hitWord": "安心",
        "rating": 4,
        "title": "カードセーバーでより安心",
        "body": "スリーブだけでは持ち運ぶ時に不安がありますが、カードセーバーにさらに入れるとほぼ折れることはないので、外でも出し入れも安心して使えます。"
      }
    ],
    "価値": [
      {
        "idx": 11,
        "hitWord": "コスパ",
        "rating": 4,
        "title": "コスパ良し",
        "body": "しっかりしていて良い感じです。コスパとても良いです！"
      },
      {
        "idx": 14,
        "hitWord": "コスパ",
        "rating": 4,
        "title": "鑑定時必須",
        "body": "鑑定時に必要なアイテムが全部そろっています。コスパも良くて満足です。"
      }
    ],
    "使いやすさ": [
      {
        "idx": 1,
        "hitWord": "使いやすい",
        "rating": 5,
        "title": "使いやすい",
        "body": "開閉がしやすいので、カードを入れるのも簡単で使いやすいです。"
      },
      {
        "idx": 2,
        "hitWord": "使いやすい",
        "rating": 5,
        "title": "値段手頃使いやすい",
        "body": "値段も手頃で使いやすい"
      },
      {
        "idx": 17,
        "hitWord": "使いやすい",
        "rating": 5,
        "title": "使い心地",
        "body": "使いやすい"
      }
    ]
  },
  "topNgramsLow": [
    {
      "gram": "エッジ",
      "count": 3
    },
    {
      "gram": "ました",
      "count": 3
    },
    {
      "gram": "セット",
      "count": 3
    },
    {
      "gram": "ている",
      "count": 3
    },
    {
      "gram": "かった",
      "count": 2
    },
    {
      "gram": "すごく",
      "count": 2
    },
    {
      "gram": "しまし",
      "count": 2
    },
    {
      "gram": "ません",
      "count": 2
    },
    {
      "gram": "ていて",
      "count": 2
    },
    {
      "gram": "接着面",
      "count": 2
    },
    {
      "gram": "着面の",
      "count": 2
    },
    {
      "gram": "面のエ",
      "count": 2
    },
    {
      "gram": "のエッ",
      "count": 2
    },
    {
      "gram": "がきつ",
      "count": 2
    },
    {
      "gram": "きつい",
      "count": 2
    }
  ],
  "topNgramsHigh": [
    {
      "gram": "やすい",
      "count": 8
    },
    {
      "gram": "カード",
      "count": 7
    },
    {
      "gram": "使いや",
      "count": 6
    },
    {
      "gram": "いやす",
      "count": 6
    },
    {
      "gram": "いです",
      "count": 5
    },
    {
      "gram": "います",
      "count": 4
    },
    {
      "gram": "つ星の",
      "count": 4
    },
    {
      "gram": "星のう",
      "count": 4
    },
    {
      "gram": "のうち",
      "count": 4
    },
    {
      "gram": "出し入",
      "count": 4
    },
    {
      "gram": "し入れ",
      "count": 4
    },
    {
      "gram": "してい",
      "count": 3
    },
    {
      "gram": "ていて",
      "count": 3
    },
    {
      "gram": "そうで",
      "count": 3
    },
    {
      "gram": "うです",
      "count": 3
    }
  ]
}