{
  "asin": "B0FLCWJ1VK",
  "productTitle": "ポケモンカードゲーム MEGA ハイクラスパック MEGAドリームex BOX",
  "scrapedAt": "2026-05-16T03:09:30.592Z",
  "reviewCount": 48,
  "reviews": [
    {
      "rating": 5,
      "title": "5つ星のうち5.0",
      "body": "Good Set. Came sealed.",
      "date": "2026年5月4日に日本でレビュー済み",
      "verified": true,
      "source": "役立った順"
    },
    {
      "rating": 5,
      "title": "シュリンク付き 正規品！騙されたと思って買ってみ飛ぶぞ✋",
      "body": "いや ココ がちランダムやでw サーチかなんかされてる前提でコレクション用に買ったけど 欲に負けて開けてしまったら メガゲンガーsarやで マジびびったw 箱の状態は潰れては無かったけどシュリンクの継ぎ目か若干クシャってたけど 正規品だった 安心して 自分の引きを楽しめるよ！ マジおすすめ！！",
      "date": "2026年5月3日に日本でレビュー済み",
      "verified": true,
      "source": "役立った順"
    },
    {
      "rating": 5,
      "title": "5つ星のうち5.0",
      "body": "good",
      "date": "2026年5月12日に日本でレビュー済み",
      "verified": true,
      "source": "役立った順"
    },
    {
      "rating": 5,
      "title": "5つ星のうち5.0",
      "body": "I'm so happy can buy it, my kid love it very much❤️",
      "date": "2026年5月4日に日本でレビュー済み",
      "verified": true,
      "source": "役立った順"
    },
    {
      "rating": 5,
      "title": "5つ星のうち5.0",
      "body": "Good",
      "date": "2026年5月8日に日本でレビュー済み",
      "verified": true,
      "source": "役立った順"
    },
    {
      "rating": 5,
      "title": "良かった",
      "body": "良かった",
      "date": "2026年5月10日に日本でレビュー済み",
      "verified": true,
      "source": "役立った順"
    },
    {
      "rating": 4,
      "title": "届きました",
      "body": "ありがとうございました。",
      "date": "2026年4月18日に日本でレビュー済み",
      "verified": true,
      "source": "役立った順"
    },
    {
      "rating": 4,
      "title": "梱包が少し⋯",
      "body": "大人気ですね。ようやく入手できました。他に注文した商品と乱雑に入れられており、箱はボロボロでした。子どもが少し残念がっていました。",
      "date": "2026年4月12日に日本でレビュー済み",
      "verified": true,
      "source": "役立った順"
    },
    {
      "rating": 4,
      "title": "Nice box",
      "body": "ほしかったカードがないんですけど、けっこよかったです。",
      "date": "2026年4月8日に日本でレビュー済み",
      "verified": true,
      "source": "役立った順"
    },
    {
      "rating": 1,
      "title": "MARなし",
      "body": "MARなしもう買わないです",
      "date": "2026年5月8日に日本でレビュー済み",
      "verified": true,
      "source": "新しい順"
    },
    {
      "rating": 1,
      "title": "詐欺",
      "body": "サーチ品封入率違うBOXではなくバラパック10がラップで巻かれて届いた",
      "date": "2026年5月4日に日本でレビュー済み",
      "verified": true,
      "source": "新しい順"
    },
    {
      "rating": 5,
      "title": "ポケモンカードbox",
      "body": "梱包綺麗でした",
      "date": "2026年5月2日に日本でレビュー済み",
      "verified": true,
      "source": "新しい順"
    },
    {
      "rating": 1,
      "title": "5つ星のうち1.0",
      "body": "Ordered 2 boxes and received 20 packs in an envelope instead.  The packs were “ hard “ to open according to my son and didn’t pull not one SR or SAR card. Packs had multiple duplicate cards.  Contacted supplier but no response.",
      "date": "2026年4月24日に日本でレビュー済み",
      "verified": true,
      "source": "★1"
    },
    {
      "rating": 1,
      "title": "5つ星のうち1.0",
      "body": "全部散包，一張SAR都沒有，全部廢卡，騙人。",
      "date": "2026年4月28日に日本でレビュー済み",
      "verified": true,
      "source": "★1"
    },
    {
      "rating": 1,
      "title": "5つ星のうち1.0",
      "body": "Impossible that I get so many ARs or SARs... either tempered or else.. I cannot be that lucky",
      "date": "2026年4月15日に日本でレビュー済み",
      "verified": true,
      "source": "★1"
    },
    {
      "rating": 1,
      "title": "サーチしてるか気になる。",
      "body": "サーチしてるのか？を疑うレベルの中身だった。",
      "date": "2026年4月26日に日本でレビュー済み",
      "verified": true,
      "source": "★1"
    },
    {
      "rating": 1,
      "title": "MA枠抜き",
      "body": "MA枠が抜かれていました。サーチされてます。購入しない方が絶対にいいです。",
      "date": "2026年4月22日に日本でレビュー済み",
      "verified": true,
      "source": "★1"
    },
    {
      "rating": 1,
      "title": "サーチ済みパック",
      "body": "サーチ済み。お勧めしません。",
      "date": "2026年4月18日に日本でレビュー済み",
      "verified": true,
      "source": "★1"
    },
    {
      "rating": 1,
      "title": "5つ星のうち1.0",
      "body": "Most likely resealed, there were almost zero pulls",
      "date": "2026年4月10日に日本でレビュー済み",
      "verified": true,
      "source": "★1"
    },
    {
      "rating": 1,
      "title": "詐欺",
      "body": "シュリンク付きボックスと表記されてますが、バラで来ました。詐欺です。",
      "date": "2026年4月14日に日本でレビュー済み",
      "verified": true,
      "source": "★1"
    },
    {
      "rating": 2,
      "title": "ありがとう",
      "body": "ありがとうございました",
      "date": "2026年4月13日に日本でレビュー済み",
      "verified": true,
      "source": "★2"
    },
    {
      "rating": 2,
      "title": "バラパック10",
      "body": "サーチ済み感がある",
      "date": "2026年4月5日に日本でレビュー済み",
      "verified": true,
      "source": "★2"
    },
    {
      "rating": 2,
      "title": ".",
      "body": "このボックスは重さでサーチされている可能性があります",
      "date": "2026年3月7日に日本でレビュー済み",
      "verified": true,
      "source": "★2"
    },
    {
      "rating": 2,
      "title": "BOXじゃなくてバラ",
      "body": "まず、BOXと表記がありますがBOXではなくバラパックで届きました。開封してみましたが、SR以上はなく、当たりはMA2枚のみでした。買わないことをオススメします。",
      "date": "2026年2月2日に日本でレビュー済み",
      "verified": true,
      "source": "★2"
    },
    {
      "rating": 2,
      "title": "SR枠抜かれて、ARは多め(個人差あり)",
      "body": "10パック×2 で20パック買いましたが、SR枠はしっかり抜かれてました。対戦用のトレーナーズ目的で買ってるので目的は達成できましたが、SR以上目的で買われる方は十分お気をつけください。ARは9枚(実質3BOX分)あったので、そちら狙いの方にはおすすめです。",
      "date": "2026年1月23日に日本でレビュー済み",
      "verified": true,
      "source": "★2"
    },
    {
      "rating": 2,
      "title": "買わない方がいい",
      "body": "多分バラで届けられたんですけど確定で入ってるカードは見当たりませんでしたsrはちょいちょいarちょいちょい後は何も出ませんでした",
      "date": "2026年1月7日に日本でレビュー済み",
      "verified": true,
      "source": "★2"
    },
    {
      "rating": 2,
      "title": "たまたま？",
      "body": "商品を開ける権利を得たと思い注文するだけです。ARすら入って無かったです。",
      "date": "2025年12月13日に日本でレビュー済み",
      "verified": true,
      "source": "★2"
    },
    {
      "rating": 2,
      "title": "箱が無い",
      "body": "シュリなし、新品同様と書いてあったが届いたら箱もありませんでした封入率は新品と同じでしたが気になる人は気をつけたほうが良いかと",
      "date": "2025年11月30日に日本でレビュー済み",
      "verified": true,
      "source": "★2"
    },
    {
      "rating": 2,
      "title": "Cards were all damaged.",
      "body": "This is my first time buying Japanese Pokemon cards, I dont know if it's common for all the cards to be damaged. The pulls were good, but since the cards are all damaged in the bottom right corner the quality immediately drops.",
      "date": "2025年12月20日にアメリカ合衆国でレビュー済み",
      "verified": true,
      "source": "★2"
    },
    {
      "rating": 3,
      "title": "カード中身",
      "body": "いいよ",
      "date": "2026年3月6日に日本でレビュー済み",
      "verified": true,
      "source": "★3"
    },
    {
      "rating": 3,
      "title": "わくわくしました。",
      "body": "期待していたカードがはいってなかったので少し残念でしたが　わくわくはさせてもらいました。ポケモンは楽しいです。",
      "date": "2026年2月23日に日本でレビュー済み",
      "verified": true,
      "source": "★3"
    },
    {
      "rating": 3,
      "title": "5つ星のうち3.0",
      "body": "Didn't come new in box like advertised. Got only 1 AR and a couple EX. Will not be buying again.",
      "date": "2026年1月21日に日本でレビュー済み",
      "verified": true,
      "source": "★3"
    },
    {
      "rating": 3,
      "title": "あたり",
      "body": "当選しました",
      "date": "2025年12月28日に日本でレビュー済み",
      "verified": true,
      "source": "★3"
    },
    {
      "rating": 3,
      "title": "早く届いた。",
      "body": "早く届きました。クリスマスプレゼントです。中身はそれなりです。",
      "date": "2025年12月25日に日本でレビュー済み",
      "verified": true,
      "source": "★3"
    },
    {
      "rating": 3,
      "title": "商品にへこみがあります",
      "body": "商品にへこみがありますから",
      "date": "2025年12月17日に日本でレビュー済み",
      "verified": true,
      "source": "★3"
    },
    {
      "rating": 3,
      "title": "(＾ω＾)",
      "body": "出品者によって梱包はもちろん、サーチされてんのかなみたいなSR0枚当たり前とか シンプルに運悪いのか分かりませんよね自分は家にいて新弾開封できてるから外れようが楽しめてるので満足です！",
      "date": "2025年12月10日に日本でレビュー済み",
      "verified": true,
      "source": "★3"
    },
    {
      "rating": 3,
      "title": "5つ星のうち3.0",
      "body": "Ok i guess... just one question. Why mine didn't came with box??? It came with just 10 packs without box... hmmmzzzz",
      "date": "2026年4月7日に日本でレビュー済み",
      "verified": false,
      "source": "★3"
    },
    {
      "rating": 3,
      "title": "baokemeng",
      "body": "tuihe,wugao",
      "date": "2025年12月29日に日本でレビュー済み",
      "verified": true,
      "source": "★3"
    },
    {
      "rating": 3,
      "title": "Great set, damaged bottoms",
      "body": "I love pokemon and I loved opening this set, got some nice cards as well. My only issue was that all of the cards in every pack had damage at the bottom :(",
      "date": "2026年3月14日にアメリカ合衆国でレビュー済み",
      "verified": true,
      "source": "★3"
    },
    {
      "rating": 4,
      "title": "5つ星のうち4.0",
      "body": "Happy to see it come in unopened boxes.  Unluckily , cannot get any SAR by opening 20pcs",
      "date": "2026年3月10日に日本でレビュー済み",
      "verified": true,
      "source": "★4"
    },
    {
      "rating": 4,
      "title": "5つ星のうち4.0",
      "body": "Delivery was fast and product was good",
      "date": "2026年3月16日に日本でレビュー済み",
      "verified": true,
      "source": "★4"
    },
    {
      "rating": 4,
      "title": "いい日だな",
      "body": "ちゃんとしたBoxでした定価でありがとうございますカナリィでました",
      "date": "2026年2月19日に日本でレビュー済み",
      "verified": true,
      "source": "★4"
    },
    {
      "rating": 4,
      "title": "定価より高いが…",
      "body": "2BOX購入してSAR1枚、SR3枚でました。どちらも2枚箱でサーチはされてなさそうです。推しポケのコダックが出たので大満足！",
      "date": "2026年2月3日に日本でレビュー済み",
      "verified": true,
      "source": "★4"
    },
    {
      "rating": 4,
      "title": "SR",
      "body": "SR入ってた。ボックスじゃなかったけど満足",
      "date": "2026年1月7日に日本でレビュー済み",
      "verified": true,
      "source": "★4"
    },
    {
      "rating": 4,
      "title": "5つ星のうち4.0",
      "body": "大丈夫。",
      "date": "2025年12月29日に日本でレビュー済み",
      "verified": true,
      "source": "★4"
    },
    {
      "rating": 4,
      "title": "特に問題無し",
      "body": "昨今問題になってはいるものの、こちらの梱包・配達は特に問題なかったです。発売日に届かない事だけが少しだけ不満点くらいで、それ以外は良好です。",
      "date": "2025年12月25日に日本でレビュー済み",
      "verified": true,
      "source": "★4"
    },
    {
      "rating": 5,
      "title": "5つ星のうち5.0",
      "body": "希望再購買，非常好的產品",
      "date": "2026年4月19日に日本でレビュー済み",
      "verified": true,
      "source": "★5"
    },
    {
      "rating": 5,
      "title": "5つ星のうち5.0",
      "body": "There a lot of Hits inludes RR to MA",
      "date": "2026年4月7日に日本でレビュー済み",
      "verified": true,
      "source": "★5"
    }
  ]
}